PaymeAPI/PaymeAPI.py
PaymeAPI/__init__.py
PaymeAPI/py.typed
PaymeAPI-1.0.4.dist-info/LICENSE
PaymeAPI-1.0.4.dist-info/METADATA
PaymeAPI-1.0.4.dist-info/WHEEL
PaymeAPI-1.0.4.dist-info/top_level.txt
PaymeAPI-1.0.4.dist-info/RECORD
